easytransfer/__init__.py
easytransfer/app_zoo_cli.py
easytransfer/feat_ext_cli.py
easytransfer/app_zoo/__init__.py
easytransfer/app_zoo/app_config.py
easytransfer/app_zoo/app_utils.py
easytransfer/app_zoo/base.py
easytransfer/app_zoo/conversion.py
easytransfer/app_zoo/feature_extractor.py
easytransfer/app_zoo/predictors.py
easytransfer/app_zoo/sequence_labeling.py
easytransfer/app_zoo/serialization.py
easytransfer/app_zoo/text_classify.py
easytransfer/app_zoo/text_comprehension.py
easytransfer/app_zoo/text_match.py
easytransfer/datasets/__init__.py
easytransfer/datasets/csv_reader.py
easytransfer/datasets/csv_writer.py
easytransfer/datasets/odps_table_reader.py
easytransfer/datasets/odps_table_writer.py
easytransfer/datasets/reader.py
easytransfer/datasets/tfrecord_reader.py
easytransfer/datasets/tfrecord_writer.py
easytransfer/engines/__init__.py
easytransfer/engines/distribution.py
easytransfer/engines/model.py
easytransfer/engines/whale_estimator.py
easytransfer/evaluators/__init__.py
easytransfer/evaluators/classification_regression_evaluator.py
easytransfer/evaluators/comprehension_evaluator.py
easytransfer/evaluators/evaluator.py
easytransfer/evaluators/kd_evaluator.py
easytransfer/evaluators/labeling_evaluator.py
easytransfer/evaluators/match_evaluator.py
easytransfer/evaluators/pretrain_evaluator.py
easytransfer/layers/__init__.py
easytransfer/layers/activations.py
easytransfer/layers/attention.py
easytransfer/layers/cnn.py
easytransfer/layers/core.py
easytransfer/layers/dam.py
easytransfer/layers/embedding.py
easytransfer/layers/encoder_decoder.py
easytransfer/layers/encoder_decoder_whale.py
easytransfer/layers/header.py
easytransfer/layers/kd.py
easytransfer/layers/mask.py
easytransfer/layers/utils.py
easytransfer/losses/__init__.py
easytransfer/losses/classification_regression_loss.py
easytransfer/losses/comprehension_loss.py
easytransfer/losses/kd_loss.py
easytransfer/losses/labeling_loss.py
easytransfer/losses/matching_loss.py
easytransfer-0.1.4.dist-info/LICENSE
easytransfer-0.1.4.dist-info/METADATA
easytransfer-0.1.4.dist-info/WHEEL
easytransfer-0.1.4.dist-info/entry_points.txt
easytransfer-0.1.4.dist-info/top_level.txt
easytransfer-0.1.4.dist-info/RECORD
