Metadata-Version: 2.1
Name: easytransfer
Version: 0.1.4
Summary: PAI EasyTransfer Toolkit
Home-page: https://github.com/alibaba/EasyTransfer
Author: PAI NLP
Author-email: minghui.qmh@alibaba-inc.com,jerry.lp@alibaba-inc.com,haojie.phj@alibaba-inc.com
License: Apache-2.0
Platform: UNKNOWN
Requires-Python: >=2.7,>=3.6
Requires-Dist: numpy
Requires-Dist: sklearn
Requires-Dist: joblib (==0.14.1)
Requires-Dist: sentencepiece
Requires-Dist: six (>=1.12.0)
Provides-Extra: tf
Requires-Dist: tensorflow (==1.12) ; extra == 'tf'
Provides-Extra: tf_gpu
Requires-Dist: tensorflow-gpu (==1.12) ; extra == 'tf_gpu'
